README.md
setup.cfg
setup.py
tbm
ssh_tunnel_boring_machine.egg-info/PKG-INFO
ssh_tunnel_boring_machine.egg-info/SOURCES.txt
ssh_tunnel_boring_machine.egg-info/dependency_links.txt
ssh_tunnel_boring_machine.egg-info/top_level.txt
tbm/__init__.py
tbm/tbm.py