Metadata-Version: 2.1
Name: ssh-tunnel-boring-machine
Version: 0.1.2
Summary: A tool for managing SSH tunnels from the command line
Home-page: https://github.com/dominicdoty/tbm
Author: Dominic Doty
Author-email: doty.dominic@gmail.com
License: MIT
Platform: UNKNOWN
Classifier: Programming Language :: Python :: 3
Classifier: License :: OSI Approved :: MIT License
Classifier: Operating System :: OS Independent
Requires-Python: >=3.6
